openstix/__init__.py
openstix/__main__.py
openstix/constants.py
openstix/customize.py
openstix/definitions.py
openstix/exceptions.py
openstix/registry.py
openstix/vocabs.py
openstix/cli/__init__.py
openstix/cli/base.py
openstix/cli/datasets/__init__.py
openstix/cli/datasets/base.py
openstix/cli/datasets/download.py
openstix/cli/datasets/models.py
openstix/cli/datasets/sync.py
openstix/cli/datasets/downloaders/__init__.py
openstix/cli/datasets/downloaders/base.py
openstix/cli/datasets/downloaders/github.py
openstix/cli/datasets/downloaders/json.py
openstix/cli/datasets/downloaders/zip.py
openstix/extensions/__init__.py
openstix/extensions/custom.py
openstix/filters/__init__.py
openstix/filters/utils.py
openstix/filters/presets/__init__.py
openstix/filters/presets/custom.py
openstix/mappings/__init__.py
openstix/mappings/base.py
openstix/mixins/__init__.py
openstix/mixins/general.py
openstix/mixins/sdo/__init__.py
openstix/mixins/sdo/campaign.py
openstix/mixins/sdo/industries.py
openstix/mixins/sdo/intrusion_set.py
openstix/mixins/sdo/locations.py
openstix/mixins/sdo/malware.py
openstix/mixins/sdo/mitigation.py
openstix/mixins/sdo/sdo.py
openstix/mixins/sdo/software.py
openstix/mixins/sdo/tool.py
openstix/mixins/sdo/vulnerabilities.py
openstix/mixins/smo/__init__.py
openstix/mixins/smo/smo.py
openstix/mixins/smo/tlp_marking.py
openstix/objects/__init__.py
openstix/objects/custom.py
openstix/properties/__init__.py
openstix/properties/types.py
openstix/providers/__init__.py
openstix/providers/abusetotal/__init__.py
openstix/providers/abusetotal/objects.py
openstix/providers/mitre/__init__.py
openstix/providers/mitre/datasets.py
openstix/providers/mitre/explorer.py
openstix/providers/mitre/objects.py
openstix/providers/mitre/presets.py
openstix/providers/oasis_open/__init__.py
openstix/providers/oasis_open/datasets.py
openstix/providers/oasis_open/explorer.py
openstix/toolkit/__init__.py
openstix/toolkit/explorer.py
openstix/toolkit/sinks.py
openstix/toolkit/sources.py
openstix-0.2.4.dist-info/METADATA
openstix-0.2.4.dist-info/WHEEL
openstix-0.2.4.dist-info/entry_points.txt
openstix-0.2.4.dist-info/licenses/LICENSE
openstix-0.2.4.dist-info/RECORD
